{
  "年度": "107",
  "學校": "國立臺灣師範大學",
  "類型": "大學",
  "教學": {
    "強化教學品質": {
      "推廣創新教學模式": [],
      "訂定核心能力，規劃課程地圖": [
        {
          "page": [
            "34",
            "47"
          ],
          "paragraph": "協助教育部制定師資職前課程基準外，亦將依此課程基準，調整與發展本校特有的中等學校教師核心能力、能力指標，與教育專業課程與專門課程。",
          "title": "協助教育部推動全國師培課綱，建立師培課程改革"
        },
        {
          "page": [
            "47",
            "49"
          ],
          "paragraph": "由各系所將標竿學習納入系所自我評鑑中，依據校務發展、系（所）務發展、評鑑委員意見、標竿系所等提出3-5個「發展重點」，並逐年列出未來5年擬達成的目標，並逐年檢核達成情形。",
          "title": "推動教學與研究單位的標竿學習以及真誠自發的自我評鑑機制"
        }
      ],
      "強化課程內容": [],
      "調整課程規劃": [
        {
          "page": [
            "31",
            "33"
          ],
          "paragraph": "將過去內隱的專業領域教學知識，整理成模組化的教學套件，使之成為可複製、可討論、能推廣的知識，進而得以回饋與再創新。",
          "title": "發展與推廣專業領域之教學模組"
        }
      ],
      "培育優良教學助教/人力": [
        {
          "page": [
            "25",
            "26"
          ],
          "paragraph": "協助教學獎助生培養執行方案時須具備之基礎教學知能，每學期規劃舉辦多場研習課程供學生選修。",
          "title": "建立教學助理及教學獎助生制度，師生共同提升教學品質及學習熱情"
        }
      ],
      "教師專業分享輔導機制": [
        {
          "page": [
            "20",
            "25"
          ],
          "paragraph": "辦理深度討論工作坊，邀請執行深度討論之教師與教學助理參加，以提升學生課堂討論之成效。未來會全面將深度討論教學法融入所有的班級。",
          "title": "推動深度討論與議題寫作之語言課程，強化思辨與專業語文能力"
        },
        {
          "page": [
            "20",
            "25"
          ],
          "paragraph": "組成大學入門教師專業社群，透過師長們腦力激盪的討論及知識分享，設計出符合學生期待的課程。",
          "title": "開設大學入門課程，規劃大學學習生涯"
        },
        {
          "page": [
            "25",
            "26"
          ],
          "paragraph": "鼓勵教師參與同儕觀課，而新進初任教師應於到職一學年內參與同儕觀課與回饋",
          "title": "建立同儕觀課制度及多元教師社群，形塑共享共學文化"
        },
        {
          "page": [
            "25",
            "26"
          ],
          "paragraph": "規劃全校觀課日，讓傑出優良或英語授課、總整課程等特定課程之經驗豐富且教學熱忱教師開放教室，促成觀課經驗之分享與傳承，營造教師同儕互助共學的氛圍。",
          "title": "建立同儕觀課制度及多元教師社群，形塑共享共學文化"
        },
        {
          "page": [
            "26",
            "28"
          ],
          "paragraph": "另為強化教師英語授課能力，規劃校內外觀課、與British Council合作規劃英語教學工作坊、辦理經驗分享座談會，為各學系教師之英語授課能力增能。",
          "title": "推動EL+X及EMI課程，提升教師英語授課能力"
        },
        {
          "page": [
            "31",
            "33"
          ],
          "paragraph": "以申請教學精進與專業社群計畫之教師為對象，媒合擅長教育研究法之教師，以共同精進創新教學模式，同時發展對應的實驗設計、選擇與設計適當的評量指標。",
          "title": "透過教學數位歷程檔案之協助，促進教學實踐研究"
        },
        {
          "page": [
            "34",
            "47"
          ],
          "paragraph": "素養導向教學與評量、跨領域課程設計、PBL社群、教材教法社群、教學實習社群等。",
          "title": "成立「師培學院」，建立領先全國的專業要求以及升等機制，確保師培生的教育訓練與教學實務能夠無縫連結"
        },
        {
          "page": [
            "34",
            "47"
          ],
          "paragraph": "透過學校支持，讓師培教師透過研討與分享，連結理論與實務，熟悉新課綱的精神以及如何轉化為師培課程，培養跨域合作的能力。",
          "title": "成立「師培學院」，建立領先全國的專業要求以及升等機制，確保師培生的教育訓練與教學實務能夠無縫連結"
        },
        {
          "page": [
            "34",
            "47"
          ],
          "paragraph": "和中學教師攜手合作，依學科領域專長與興趣發展出教師專業學習社群，及師資培育之教材以及對應的教學方法，建立各項師資培育的特色教學。",
          "title": "協助教育部推動全國師培課綱，建立師培課程改革"
        }
      ],
      "健全教師（學）評鑑制度": [],
      "推動多元升等": [
        {
          "page": [
            "59",
            "64"
          ],
          "paragraph": "制定「推動大學社會責任計畫實施辦法」，例如在升等部份，未來將配合教學實務研究之多元升等，提供投入USR之教師有多元的升等管道。",
          "title": "校內支援與獎勵辦法"
        }
      ],
      "健全教學獎勵制度": [
        {
          "page": [
            "25",
            "26"
          ],
          "paragraph": "除鼓舞教學表現優良教師之外，將邀請其擔任教學諮詢教師，提供同儕觀課與回饋、教學知能諮詢或經驗交流分享等協助。",
          "title": "獎勵教學優良教師與優良導師，結合學術研究以發展創新之教學策略"
        },
        {
          "page": [
            "25",
            "26"
          ],
          "paragraph": "除教學優良獎勵制度外，也將提供經費補助，讓老師可以發展創新之教學策略，並結合學術研究以探討創新教學之實證效果，並協助推廣到校內外之教學實踐上。",
          "title": "獎勵教學優良教師與優良導師，結合學術研究以發展創新之教學策略"
        },
        {
          "page": [
            "31",
            "33"
          ],
          "paragraph": "後續將設計獎勵機制，鼓勵更多教師將教學實務轉化成高等教育研究成果。",
          "title": "透過教學數位歷程檔案之協助，促進教學實踐研究"
        }
      ],
      "減輕教師教學負擔": [],
      "建立教學改善回饋系統": [
        {
          "page": [
            "20",
            "25"
          ],
          "paragraph": "進行「通識課程學生課堂行為調查問卷」（線上問卷調查），以瞭解學生在通識課程的課堂行為，施測及分析完成後，將邀請通識相關學者專家、學生座談，共同討論學生課堂行為，檢討通識課程發展方向，及設計優質的課程與教學策略。",
          "title": "改革通識課程及學習評量機制，提升核心素養"
        },
        {
          "page": [
            "25",
            "26"
          ],
          "paragraph": "規劃焦點座談會、期中期末晤談，將教學獎助生的意見回饋教師與系所，使教師與系所更瞭解獎助生學習情況，以提供適切地引領與教導。",
          "title": "建立教學助理及教學獎助生制度，師生共同提升教學品質及學習熱情"
        },
        {
          "page": [
            "31",
            "33"
          ],
          "paragraph": "將介接本校教務系統與各類教學平台之資料，以利教學成效證據的彙整；利用學習數據、資料採礦，發現有意義的學習樣態或規則，回饋授課教師及學生，並便利於樣態或規則的評估。",
          "title": "透過教學數位歷程檔案之協助，促進教學實踐研究"
        },
        {
          "page": [
            "31",
            "33"
          ],
          "paragraph": "結合各學系、各行政單位，一起建立學生從高中、大學、就業等完整個人學習檔案，並利用本校擅長的學習科學知能進行各種分析，評估學生學習成效，提供院系所及學校進行各項教與學策略改進及學術單位調整參考。",
          "title": "整體評估學生學習成效，確保教育品質"
        },
        {
          "page": [
            "31",
            "33"
          ],
          "paragraph": "針對學生學習成效進行有效的異質性資料的整合和分析；並透過統計分析相關技術，建立教育決策預測模型，定期蒐集與更新數據資料，動態修正與檢驗模型，以達到模型預測的正確性和效果性。",
          "title": "完備校務研究（IR）體系，定期巡視校務資料並提供檢測報告建議，持續追蹤學生學習成效，提供校務發展之證據基礎"
        },
        {
          "page": [
            "34",
            "47"
          ],
          "paragraph": "本校將積極強化高等教育的研究、政策與實務之間的連結，除了協助執行創新教學的教師進行研究，且將由學習科學研究中心界定前瞻重要教育問題並進行實徵研究。",
          "title": "擴充高等教育教學研究能量與成果，邁向全球知名高等教育教學成效大學"
        },
        {
          "page": [
            "34",
            "47"
          ],
          "paragraph": "本校將發展適性與問題導向之精準教育技術、建立跨資料平台的大數據分析系統，透過大數據分析一般化及個人化教育資料，產生教學決策知識庫及學生完整學習側寫的學生模型，依此提供學生精準教育。",
          "title": "開創多元學習需求的精準教育典範，實現教育研究世界頂尖之願景"
        },
        {
          "page": [
            "64",
            "65"
          ],
          "paragraph": "評量工具的發展，則朝向串連題庫系統與成績系統資料，分析學生試題的答題情況，同時針對每份評量結果呈現評分指引，讓學生更清楚知道等級成績代表的意義，也讓教師獲得更多有助於改善教學的訊息。",
          "title": "開發素養評量工具、提供教學之科技輔助，落實十二年國教政策目標"
        },
        {
          "page": [
            "64",
            "65"
          ],
          "paragraph": "期望透過標準本位評量的推動，讓教師有機會重新檢視課程（課綱）－教學－評量三者間的連結，協助國內教育品質的全面提升。",
          "title": "開發素養評量工具、提供教學之科技輔助，落實十二年國教政策目標"
        }
      ],
      "課程外審": [],
      "教學單位國際認證": [
        {
          "page": [
            "26",
            "28"
          ],
          "paragraph": "師培處與三學系根據特色規劃國際文憑學程課程，通過認證後將會對校內師資生進行招生，精緻化學理與實務兼顧的「國際文憑教師證照（International Baccalaureate Educator Certificate, IBEC）」培用合一的課程內容。",
          "title": "推動國際文憑（IB）教師認證，提升師培生國際移動力"
        },
        {
          "page": [
            "26",
            "28"
          ],
          "paragraph": "辦理IB師培工作坊，輔導其獲得國內教師證照與國際文憑師資證照。未來會將四學程的成功經驗推廣至其他系所，視不同系所師資生的需求，發展IBEC學程。",
          "title": "推動國際文憑（IB）教師認證，提升師培生國際移動力"
        },
        {
          "page": [
            "34",
            "47"
          ],
          "paragraph": "擴充數個以英文授課之教育學程科目，幫助學生學習不同文化下所需專業教學知識與技能，以及學生學習特徵、國外教育環境等知識，達成三個學程之課程設計，協助通過「國際文憑組織」師培課程認證，發展成為臺灣第一所IBEC師培機構。",
          "title": "發展國際文憑（IB）教師學程，爭取認證，協助教師海外任教"
        }
      ],
      "成立教學品保委員會": [],
      "提升教師群專業度": []
    },
    "跨領域學習": {
      "規劃跨領域學位（分）學程": [],
      "鼓勵輔系、雙主修": [
        {
          "page": [
            "28",
            "30"
          ],
          "paragraph": "鼓勵學系因應潮流，開放心胸，開放更多雙主修、輔系、學分學程的名額，滿足學生跨域學習需求。",
          "title": "降低雙主修及輔系學分，放寬修課限制，建立跨域學習空間"
        }
      ],
      "跨領域教學": [
        {
          "page": [
            "20",
            "25"
          ],
          "paragraph": "實現跨學制、跨領域合作，培養學生動手實作、問題解決之能力。",
          "title": "開設微學分生活技能通識，培養動手實作能力"
        },
        {
          "page": [
            "64",
            "65"
          ],
          "paragraph": "本校將持續整合教育政策相關計畫，透過跨領域、跨院系所及跨機構之交流活動與整合平台，出版與傳播重要教育議題研究報告，促進教育政策對研究建議的採用，並強化研究結果融入教學實務的機制，讓優質的教育政策能夠更完整的落實於學校實務現場。",
          "title": "擬定方案及白皮書，協助政府規劃執行"
        }
      ]
    },
    "提高學習自由度及彈性": {
      "調降系必修學分": [
        {
          "page": [
            "28",
            "30"
          ],
          "paragraph": "檢討並降低各學系雙主修、輔系學分數，使之更為合理。",
          "title": "降低雙主修及輔系學分，放寬修課限制，建立跨域學習空間"
        }
      ],
      "微學分（彈性學分）": [
        {
          "page": [
            "20",
            "25"
          ],
          "paragraph": "未來將納入行銷企管、生活APP、木工製造等實作課程，並擴大結合新北地區優質高職師資與設備，開設微學分生活技能通識",
          "title": "開設微學分生活技能通識，培養動手實作能力"
        }
      ],
      "開設入學前先修課程": [
        {
          "page": [
            "20",
            "25"
          ],
          "paragraph": "新生定向輔導計畫是為期四天營隊，採自由參加方式，讓新生實地走訪並操作各項設施以熟悉校園環境與文化。",
          "title": "推動新生定向輔導計畫-新生營，協助新生適應大學生活"
        },
        {
          "page": [
            "20",
            "25"
          ],
          "paragraph": "除了教育學院及理學院持續規畫符應各院系特色的課程之外，未來將推動所有學院都開設大學入門課程。",
          "title": "開設大學入門課程，規劃大學學習生涯"
        }
      ],
      "深碗課程": []
    },
    "人才國際化": {
      "增進外語能力": [],
      "多元文化/文化交流": [
        {
          "page": [
            "47",
            "49"
          ],
          "paragraph": "「百大城市」亦為落實校園國際化的重要行動方案之一，本校為增進全球目標區域之交流，精選百大重點城市，設定三階段目標，選擇定位於重點城市之知名大學，簽署合作協議，並提高師生交流合作機會，進一步擴展國際移動力。",
          "title": "鼓勵系所進行國際合作研究，推動「一系一國際學術合作案」與「全球百大城市實質國際交流」計畫"
        }
      ],
      "辦理海外參訪或移地教學": [
        {
          "page": [
            "34",
            "47"
          ],
          "paragraph": "Push則是學生赴歐、美、日等先進國家合作辦理「跨國設計整合工作坊」；或至海外藝術單位參與專業研修、實習及訪察研究。",
          "title": "延攬國際級藝術人文大師，開創特殊選才招生，培育頂尖藝術人才"
        }
      ],
      "交換學生": [],
      "雙聯學位": [],
      "推動英語授課/全英語學程": [
        {
          "page": [
            "26",
            "28"
          ],
          "paragraph": "目前推動以各院、系（所）整合數門既有碩、博士課程，加上院共同課程，組成一系列以全英語授課之學位課程，提供外籍生修讀並取得學位，規劃未來達到80％以上系所有全英語學位學程。",
          "title": "推動全英語授課碩博士學位學程，系所全面招收外籍生"
        },
        {
          "page": [
            "26",
            "28"
          ],
          "paragraph": "先以院為單位，開設院屬專業英文課程，持續擴大到針對各系所的課程。",
          "title": "推動EL+X及EMI課程，提升教師英語授課能力"
        }
      ],
      "生源國際化（及其配套措施）": [
        {
          "page": [
            "26",
            "28"
          ],
          "paragraph": "結合台大、台科大規劃東南亞師資培育學院分部，部分課程以數位學習模式授課，協助培養越南和印尼中小學教師。",
          "title": "結合臺灣大學系統，建立東南亞分校"
        }
      ],
      "國際學位學程/學院": [],
      "招聘外籍老師（或邀請授課）": [],
      "培養華語教學人才": [
        {
          "page": [
            "66",
            "67"
          ],
          "paragraph": "配合國家華語政策之發展，培育各類華語教育人才輸出全球。未來將透過前端華語文科技研發成果，建立國內外產學合作網絡，強化國際影響力，帶領臺灣成為「華語文科技產業島」。",
          "title": "建設臺灣為華語文科技產業島，興盛華語文教育人才培育產業"
        },
        {
          "page": [
            "66",
            "67"
          ],
          "paragraph": "本校將於109年由「臺師大新創控股事業股份有限公司」投資華語文與科技研究中心之研發成果，設立「華語文科技公司」，聘請專業經理人管理與營運。",
          "title": "建設臺灣為華語文科技產業島，興盛華語文教育人才培育產業"
        },
        {
          "page": [
            "34",
            "47"
          ],
          "paragraph": "在習得歷程與機制基礎研究，結合行為科學、腦科學以及計算神經科學，建構以證據為基礎，不受限於西方語言學理論，專為解決華語學習困難為導向之診斷、預測、與訓練工具的理論基礎。",
          "title": "持續提升本校華語文基礎研究與華語文科技之技術研發"
        },
        {
          "page": [
            "34",
            "47"
          ],
          "paragraph": "在語言科技研究，採用習得歷程與機制基礎研究團隊的學習原理，設計強效的診斷、預測、與訓練工具，以人工智慧（包含深層學習和機器學習）技術，使機器進行語言理解為目標，提供學習者更感性（例如，可判斷學習者情緒變化）的人機互動功能，建構更具趣味性與學習效果之學習平台。",
          "title": "持續提升本校華語文基礎研究與華語文科技之技術研發"
        },
        {
          "page": [
            "34",
            "47"
          ],
          "paragraph": "在教學應用與評量，開發專門應用於上述數位教學平台之教學法與教材，提高教學平台使用效率，達到本中心以線上教學佈局全球華語文教學產業的目標。",
          "title": "持續提升本校華語文基礎研究與華語文科技之技術研發"
        },
        {
          "page": [
            "34",
            "47"
          ],
          "paragraph": "本校將由「臺師大新創控股事業股份有限公司」投資華語文與科技研究中心之研發成果，設立「華語文科技公司」，聘請專業經理人管理與營運。",
          "title": "協助帶領臺灣各高校華語教學中心，建設臺灣為華語文科技產業島"
        },
        {
          "page": [
            "34",
            "47"
          ],
          "paragraph": "短期階段：本校「華語文與科技研究中心」與臺灣北、中、南各地設有華語課程之大專院校在華語教學上有密切的合作交流。",
          "title": "協助帶領臺灣各高校華語教學中心，建設臺灣為華語文科技產業島"
        },
        {
          "page": [
            "34",
            "47"
          ],
          "paragraph": "中期階段：本校是全世界的華語學習者心中首選的華語教學機構，尤其是東南亞與東北亞的多家教學機構已與本校建立了實質友好的交流管道，並對本校的華語教學產品表達高度興趣。",
          "title": "協助帶領臺灣各高校華語教學中心，建設臺灣為華語文科技產業島"
        },
        {
          "page": [
            "34",
            "47"
          ],
          "paragraph": "長期階段：汲取初中期的在地經驗後，在中期建立品牌形象與知名度，長期將透過網路行銷手法，吸引更多對華語有興趣之學習者。",
          "title": "協助帶領臺灣各高校華語教學中心，建設臺灣為華語文科技產業島"
        },
        {
          "page": [
            "34",
            "47"
          ],
          "paragraph": "本校將持續向我國駐外館處與各大學校院、華語學校、華語中心、社群媒體等進行電郵網路宣傳，招收全球各國華語文教育高階專業人才。",
          "title": "開設線上華語師資專班，佈局華語文全球影響力"
        },
        {
          "page": [
            "67",
            "69"
          ],
          "paragraph": "未來將持續以「海外代理」模式擴大測驗市場，增設國家數與考點；積極整合國內各地的華語資源，齊心協力打造臺灣華語教育品牌。",
          "title": "運用華測會測驗資源，以非政治方式開通外交活路"
        },
        {
          "page": [
            "67",
            "69"
          ],
          "paragraph": "讓僑居地未來種子教師在本校學習，並於實習後回到僑居地擔任教師，亦或留臺教授僑居地語言，培養新南向國家之師資，深化臺灣與東南亞國家之互動及聯盟關係，為臺灣「華語文與僑生教育新南向政策」帶來新契機。",
          "title": "建立國際化華語僑教品牌大學，培養新南向政策之關鍵媒介"
        }
      ]
    },
    "提升基礎能力": {
      "強化國文能力": [],
      "強化數理能力": [],
      "強化寫作能力": [],
      "強化表達溝通能力/領導能力": [
        {
          "page": [
            "20",
            "25"
          ],
          "paragraph": "透過多元語文增能競賽，讓學生對特定主題進行批判性分析思考，同時提高其活用國文及英文的機會，有系統地訓練強化學生思辯及溝通表達能力。",
          "title": "推動深度討論與議題寫作之語言課程，強化思辨與專業語文能力"
        }
      ]
    },
    "提升實作能力": {
      "推動各類競賽（實作能力）": [
        {
          "page": [
            "34",
            "47"
          ],
          "paragraph": "創融學院進一步將透過跨校合作、創意發明、設計實務及產學合作方式，進行產業界及學術界設計創新與資源之交流。",
          "title": "成立三創、三共、三跨的「創融學院」，培養文創專業人才"
        }
      ],
      "建立校外競賽鼓勵機制": [],
      "呈現、檢核或評估實作成果": [
        {
          "page": [
            "34",
            "47"
          ],
          "paragraph": "並於每年年底舉辦成果發表會暨成果展覽，共同創造新的學習模式。",
          "title": "成立三創、三共、三跨的「創融學院」，培養文創專業人才"
        }
      ],
      "開設增進實務能力導向課程": [
        {
          "page": [
            "30",
            "31"
          ],
          "paragraph": "本學分學程主要提供社團經營的「實務」課程，而「專業學識」課程則由各系所開設相關之理論學科。",
          "title": "開辦社團人專業領導培力學分學程，玩出人才軟實力"
        }
      ],
      "聘請業師或雙師協同教學": [
        {
          "page": [
            "34",
            "47"
          ],
          "paragraph": "本校藝術學院將以「Pull & Push」雙P併行培育頂尖藝術人才，Pull是指延攬國際設計大師或知名藝術學者專家。",
          "title": "延攬國際級藝術人文大師，開創特殊選才招生，培育頂尖藝術人才"
        },
        {
          "page": [
            "34",
            "47"
          ],
          "paragraph": "接著靠選拔在學之優秀學生，聯繫各項國際音樂交流資源，進行各項特殊音樂才能培訓，邀請世界級之大師來台授課。",
          "title": "延攬國際級藝術人文大師，開創特殊選才招生，培育頂尖藝術人才"
        }
      ],
      "提升教師實務能力": [],
      "建立/強化實習制度": [
        {
          "page": [
            "26",
            "28"
          ],
          "paragraph": "本校將持續與國外知名大學簽署合作交流協議、境外臺灣學校簽署實習交流協議。",
          "title": "建立海外實習制度，培養國際就業力"
        },
        {
          "page": [
            "26",
            "28"
          ],
          "paragraph": "推動系所與國外企業機構簽署合作交流協議，並提高每年薦送學生赴國外企業機構進行見習的人次。",
          "title": "建立海外實習制度，培養國際就業力"
        },
        {
          "page": [
            "34",
            "47"
          ],
          "paragraph": "未來將積極與國內外IB學校或國際學校簽訂合作契約，輔導學生進行實習與就業。",
          "title": "發展國際文憑（IB）教師學程，爭取認證，協助教師海外任教"
        }
      ],
      "實施課程分流制度": []
    },
    "提升專業/證照能力": {
      "開設證照專業課程": [],
      "專業技能檢定之輔導機制": [
        {
          "page": [
            "34",
            "47"
          ],
          "paragraph": "建立師資雙證照機制，逐步輔助校內師資生修習與取得雙證照（部訂教師、國際文憑），提升海外任教人數。",
          "title": "發展國際文憑（IB）教師學程，爭取認證，協助教師海外任教"
        }
      ],
      "制訂專業證照獎勵辦法": [],
      "學士後專業教育": [],
      "其他": [
        {
          "page": [
            "34",
            "47"
          ],
          "paragraph": "透過運動科學原理與技術對臺灣選手進行訓練，經由客觀的數據來指出運動員的優缺點以讓教練能夠看見訓練成效並改善缺點，並依據每位運動員之特殊需求擬定客製化訓練處方，經由運動科學有效增進運動員之技術、體能及心理素質，讓臺灣選手能在國際賽場上發光發熱。",
          "title": "建立科學化訓練，有效提升運動選手在國際賽場上的競爭力"
        },
        {
          "page": [
            "67",
            "69"
          ],
          "paragraph": "科教、藝術及運動科學等領域，未來在菁英人才培育上將持續以創造高階專業人士為目標，參與各項國際競賽與交流，並爭取各類國際競賽與學術組織要職。",
          "title": "培養科教、藝術及運動科學國際菁英人才、啟動多元外交模式"
        }
      ]
    },
    "數位化": {
      "建置開放式線上課程": [
        {
          "page": [
            "26",
            "28"
          ],
          "paragraph": "積極建置數位課程整合平台、發展數位課程設計模式與流程，並提升開課教師與工作團隊所需專業職能。",
          "title": "成立「網路大學」，擴展國際學生來源"
        },
        {
          "page": [
            "31",
            "33"
          ],
          "paragraph": "善用新興技術，開發智慧教學平台功能及介面，結合同步及非同步教學設施與各種載具，建立無所不在的學習環境。",
          "title": "發展與推廣專業領域之教學模組"
        }
      ],
      "開發數位學習課程": [
        {
          "page": [
            "67",
            "69"
          ],
          "paragraph": "國際數位學位主要招收全球在職人士（不含陸生），學生免入境，透過數位平台學習，符合本校碩士畢業規定與要件即授予碩士學位。",
          "title": "開設線上課程及專班，強化海外師資培育的影響力"
        },
        {
          "page": [
            "67",
            "69"
          ],
          "paragraph": "本專班採獨立招生，透過我國駐外館處與各大學校院、華語學校、華語中心、社群媒體等管道進行宣傳，遍及亞洲、北美洲、中美洲、南美洲、歐洲等地區，能透過數位課程與學位授與，達成文化外交的功能。",
          "title": "開設線上課程及專班，強化海外師資培育的影響力"
        }
      ],
      "教材雲端化": [],
      "數位教學創新": [
        {
          "page": [
            "20",
            "25"
          ],
          "paragraph": "科技融入體育教學，利用運動教學APP、穿戴式裝置與行動學習等，每年依據研究結果修正操作方法與介入課程，做為未來推動多樣化體育課程之參考。",
          "title": "推動適性多元之創新體育課程，培養終身運動習慣"
        },
        {
          "page": [
            "20",
            "25"
          ],
          "paragraph": "遠程將發展能符應各學院、各學系需求的CT課程，此外，為了以創新模式進行CT課程教學，未來將發展跨作業系統及行動載具之視覺化程式設計教學支援平台。",
          "title": "開設運算思維與程式設計課程（Computational Thinking, CT）及CT+X課程，客製化各學院需求，發展程式設計應用於專業領域之能力"
        },
        {
          "page": [
            "34",
            "47"
          ],
          "paragraph": "本校在數位學習科技的研發，已具有數項領先全球的應用技術，未來將開發成為實用學習輔助裝置、職前訓練輔助裝置、情意態度輔助裝置，形成結合教育底蘊與高科技應用的新商業模式，並協助臺灣數位學習廠商或教育軟體業者提升產業效能。",
          "title": "深化教學科技技術，建立教育產業"
        }
      ],
      "電子學習歷程（e-Portfolio）": [
        {
          "page": [
            "55",
            "58"
          ],
          "paragraph": "未來將新置學生數位學習歷程系統介接項目，如師資培育與就業輔導處相關系統、學生體適能資料庫及學務相關系統等。",
          "title": "設立「學生數位學習歷程檔案系統」，完整本校學生的學涯履歷"
        },
        {
          "page": [
            "34",
            "47"
          ],
          "paragraph": "未來也將針對學習歷程平台進行推廣，讓全國的體育教學都有機會可以利用此平台來瞭解學生的體育課學習過程以及個人運動紀錄",
          "title": "以素養本位的體育教學，實踐K−16幼兒到大學的身體素養培育目標"
        },
        {
          "page": [
            "34",
            "47"
          ],
          "paragraph": "建立師資生學習檔案，記錄本校師資生邁向教職進程的相關資料，做為未來師資生申請各項證書、掌握師資生學習歷程，提供相關數據分析運用。",
          "title": "協助教育部推動全國師培課綱，建立師培課程改革"
        },
        {
          "page": [
            "34",
            "47"
          ],
          "paragraph": "目前K-12各學習階段已建置體適能資料庫，「BodyBook」未來將結合高中端學習資料庫，健全K-16學生體育學習歷程。",
          "title": "以素養本位的體育教學，實踐K−16幼兒到大學的身體素養培育目標"
        }
      ],
      "典藏文獻史料數位化": [
        {
          "page": [
            "34",
            "47"
          ],
          "paragraph": "即將串連此二深具國際性兼具專業技術的院級典藏保存中心，建構師大「藝術文物傳承平台」，以期資源互惠，整合有形的修復技術與無形的數位典藏，以邁向具國際科技性典藏保存的平台發展。",
          "title": "打造全球知名的「文物保存修復中心」與「音樂數位典藏中心」"
        }
      ]
    },
    "資訊力": {
      "開設程式設計課程": [],
      "開設資訊學程/課程": [],
      "辦理程式設計競賽": [],
      "強化基本資訊能力": [
        {
          "page": [
            "20",
            "25"
          ],
          "paragraph": "近程先研發「運算思維與程式設計」教學共同教材、視覺化程式設計教學支援平台的開發，以及藉由實驗種子班級反饋來修正教材。",
          "title": "開設運算思維與程式設計課程（Computational Thinking, CT）及CT+X課程，客製化各學院需求，發展程式設計應用於專業領域之能力"
        }
      ]
    },
    "博雅教育": {
      "通識課程革新": [],
      "辦理藝術展覽或藝文活動": [
        {
          "page": [
            "34",
            "47"
          ],
          "paragraph": "本校將於師大美術館落成後，與專業民間國際策展團隊產學合作，建立臺灣全新博物館營運模式，組織成立學校與社區藝文志工，定期舉辦國際級藝術展覽，並配合策展開展專業美術教育活動如講習或工作營。",
          "title": "形塑環繞「師大美術館」的藝文特區，建立全臺藝術新地標"
        },
        {
          "page": [
            "34",
            "47"
          ],
          "paragraph": "中期將調查與整合永康商圈與師大商圈之人文藝術設計之商家，整合所有社區資源進行巷弄美學資料庫，建構師大藝文特區完整巷弄美學之散步道，形塑為「師大藝文特區」。",
          "title": "形塑環繞「師大美術館」的藝文特區，建立全臺藝術新地標"
        },
        {
          "page": [
            "34",
            "47"
          ],
          "paragraph": "透過時藝新媒體公司全體進駐本校，結合本校既有的人文藝術資源，以聯合策展、美學教育、文創產業集結、表演活動、學術研討與專書發表等方式，發揮系所學術專業，建立知名度並對藝術界有所貢獻。",
          "title": "形塑環繞「師大美術館」的藝文特區，建立全臺藝術新地標"
        },
        {
          "page": [
            "66",
            "67"
          ],
          "paragraph": "運用藝術文化的資產與專業，推行多元跨界資源共享，協助國立故宮博物院南部院區創建「文創體驗館」與「文化展演空間」，發展創新之「文創體驗模式」的社區新價值。",
          "title": "樹立文創產業典範模式，將藝文創作價值極大化"
        },
        {
          "page": [
            "66",
            "67"
          ],
          "paragraph": "本校將建置「藝術銀行」，透過優秀校友的藝術與音樂作品的數位典藏與借展，創造新式藝術經營模式。",
          "title": "樹立文創產業典範模式，將藝文創作價值極大化"
        },
        {
          "page": [
            "55",
            "58"
          ],
          "paragraph": "107年甫完工營運之「師大美術館」，將做為展示本校典藏畫作及傑出校友畫作之空間，彰顯本校於臺灣美術史之重要貢獻，並結合民間營運機構引進各類型國際級展覽，邀請師生及民眾共襄盛舉，成為培養人文藝術素養與拓展國際視野的文化新亮點。",
          "title": "活化校園資產，提升財產運用效能"
        },
        {
          "page": [
            "55",
            "58"
          ],
          "paragraph": "未來將逐年完成「青田街藝術展示空間活化」（配合美術館營運，結合社區發展，拓展文化創意據點）、「師大路眷舍收回再利用」（收回師大路眷屬宿舍變更為教學辦公使用，配合產學發展提升資產活化效益）。透過改建閒置空間、珍視文化資產的保存及活化再利用，營造與社區民眾良好互動的開放性校園。",
          "title": "活化校園資產，提升財產運用效能"
        }
      ],
      "品德教育": [],
      "服務學習": [],
      "其他": []
    },
    "培養自主學習能力": {
      "閱讀計畫補助": [],
      "自主學習計畫獎勵機制": [],
      "自主學習資源共享平台": [],
      "激勵社團相關活動與競賽": [],
      "住宿書院（及自主學習相關課程與活動）": [
        {
          "page": [
            "20",
            "25"
          ],
          "paragraph": "金牌書院設置為選手量身打造的學分學程，開設E化行動課程，為選手們補強因練習而無法參與的課程，並透過多益精進班、英語會話班、專業證照班、參與國內外移地訓練，提供全方位支持與輔導。",
          "title": "推動多元型態特色書院制度"
        }
      ]
    },
    "培育創新創業人才": {
      "創新創業學程或課程": [
        {
          "page": [
            "30",
            "31"
          ],
          "paragraph": "持續開辦「創業學分學程」，並增加國際企業管理與實習課程，提升學生國際事業管理視野。",
          "title": "擴大開設創業學分學程，培育特色產業創業人才"
        },
        {
          "page": [
            "34",
            "47"
          ],
          "paragraph": "創融學院達三創、三共、三跨之共同合作與資源共享原則，並做為培育優秀設計人才之參考，也推動課程和研習內容在三校之間延續或擴散，資源與成果共享。",
          "title": "成立三創、三共、三跨的「創融學院」，培養文創專業人才"
        }
      ],
      "育成學生創業團隊": [
        {
          "page": [
            "30",
            "31"
          ],
          "paragraph": "支援學生創業團隊成立新創公司，後續將銜接控股公司與育成輔導；辦理創業競賽，拔尖優秀創業團隊。",
          "title": "擴大開設創業學分學程，培育特色產業創業人才"
        }
      ],
      "建立完整的創業輔導機制": [],
      "聘請業師參與育才": [],
      "舉辦創業團隊競賽": [],
      "發明展（或競賽）鼓勵機制": [],
      "其他創業輔導及補助": [
        {
          "page": [
            "30",
            "31"
          ],
          "paragraph": "整合校園創業資源，提供創業設備環境。",
          "title": "擴大開設創業學分學程，培育特色產業創業人才"
        },
        {
          "page": [
            "30",
            "31"
          ],
          "paragraph": "協助創業競賽與創業學程具潛力團隊進行創業，除實際進行天使投資外，並加以育成輔導，避免學生面臨初期創業資金、場域、營運實作及管理經驗缺乏而無法實創業之困境。",
          "title": "成立新創事業投資控股公司，活絡校內創業創新氣氛"
        }
      ]
    },
    "健康力": {
      "促進學生生理健康": [
        {
          "page": [
            "20",
            "25"
          ],
          "paragraph": "配合本校體適能檢測期程，陸續輸入學生檢測紀錄，同時逐步匯入過去本校體適能檢測紀錄，健全體適能資料庫並建立常模。",
          "title": "推動適性多元之創新體育課程，培養終身運動習慣"
        }
      ],
      "促進學生心理健康": []
    },
    "就業力": {
      "強化職場連結": [],
      "生涯/職涯輔導": [
        {
          "page": [
            "28",
            "30"
          ],
          "paragraph": "透過校內全方位輔導機制，提供統整性的職涯服務，同時推動系所實習機制，開設實習課程，鼓勵學生參與職場實習。",
          "title": "強化全方位職輔機制，提升學生就業競爭力"
        },
        {
          "page": [
            "28",
            "30"
          ],
          "paragraph": "藉由就業博覽會、職涯測驗、企業參訪、延攬產業師資協助教學、職涯銜接準備等活動培育學生職能，同時提供數位化職業資訊以開展就業。",
          "title": "強化全方位職輔機制，提升學生就業競爭力"
        }
      ],
      "就業博覽會": [],
      "畢業生流向調查": [
        {
          "page": [
            "28",
            "30"
          ],
          "paragraph": "針對在校學生、畢業校友、企業雇主等互動關係人先進行畢業生就業狀況、雇主滿意度調查，做為職涯輔導規劃之依據。",
          "title": "強化全方位職輔機制，提升學生就業競爭力"
        }
      ],
      "雇主滿意度調查": []
    },
    "其他": {
      "充實與改善硬體設備": [],
      "跨校學習資源整合與共享": [
        {
          "page": [
            "28",
            "30"
          ],
          "paragraph": "持續開放與增加三校間學程修習名額，拓展學生學習視野。提升課程質與量，降低各校各自開課成本。加速課程資訊交換頻率，降低三校課程資訊落差。",
          "title": "鼓勵學生跨校選課，增進跨校跨域共學體驗"
        },
        {
          "page": [
            "28",
            "30"
          ],
          "paragraph": "整合三校全英語課程，提供學生修習全英語課程之機會，並以本校現有的國際文化學分學程為基礎，三校合作規劃全英語國際文化學分學程。",
          "title": "鼓勵學生跨校選課，增進跨校跨域共學體驗"
        },
        {
          "page": [
            "28",
            "30"
          ],
          "paragraph": "積極推動各系、所、學位學程與合作學校擬具跨校共同指導合作協議書。跨校共同指導之研究生，可比照交換學生身分，至合作學校接受指導或修習相關學分，並擁有合作學校正式核發之成績單或修課證明。",
          "title": "推動研究生跨校共同指導機制"
        },
        {
          "page": [
            "59",
            "64"
          ],
          "paragraph": "美國在臺協會與天下雜誌合作，以花蓮夥伴學校為中心點，引進「閱讀行動數位書車」（Mobile American Corner）提供電子書、iPads和視訊等設備，豐富偏鄉學生的學習資源。",
          "title": "爭取國際資源投入，在地串聯發展特色教學模組，並向海外推廣"
        },
        {
          "page": [
            "59",
            "64"
          ],
          "paragraph": "PASSION團隊亦推動「PASSION偏鄉優質教育微學程」，建構修課、培訓及實習的補救教學師資培育模板，未來將此師培模板推廣至全臺與世界各地所需之處，讓補救教學受到廣泛的重視，及強化補救教學師資的能力。",
          "title": "爭取國際資源投入，在地串聯發展特色教學模組，並向海外推廣"
        }
      ],
      "學生輔導": [
        {
          "page": [
            "64",
            "65"
          ],
          "paragraph": "未來將此行動方案推廣至東南亞及中國大陸之境外臺灣學校，提供旅外台商子女之學習扶助。",
          "title": "研發多元診斷系統，提供適性教學，以回應特殊需求、弭平成就落差"
        },
        {
          "page": [
            "64",
            "65"
          ],
          "paragraph": "PASSION教學團隊透過增能工作坊及到校諮詢，將教學配套推行至現有實施補救教學的國民中學，協助教師運用系統篩選出需要強化學科的學生，及運用各科PASSION教材誘發學生學習動機，提升學習成效。",
          "title": "研發多元診斷系統，提供適性教學，以回應特殊需求、弭平成就落差"
        }
      ]
    }
  },
  "研究": {
    "提升研究能量": {
      "制訂限期升等相關規範": [],
      "增加授課時數制度彈性": [],
      "強化落實評鑑制度": [],
      "提供研究經費支援": [],
      "提供研究人力支援": [],
      "提供研究獎勵及補助": [],
      "成立研究中心": [],
      "與國內其他研究單位合作": [],
      "設置研發創新獎項": [],
      "前瞻性頂尖研究": [],
      "辦理學術講座": [],
      "提供研究分享輔導機制": []
    },
    "延攬優秀人才及留才": {
      "落實彈性薪資": [],
      "加強推動特聘講座制度": [],
      "設立專款支援人才聘任": [],
      "強化教師福利": [],
      "吸引外籍人才相關措施": [],
      "建立優秀人才資料庫": []
    },
    "學術國際化": {
      "國際實驗室交流合作": [],
      "跨國合作研究": [
        {
          "page": [
            "47",
            "49"
          ],
          "paragraph": "為了培育具潛力的特色領域組成研究團隊或申請成立跨國中心，本校將持續補助與媒合校內教研人員，透過世界大學排名分析資料與本校姐妹校資料，推薦重點合作學校與合作領域。",
          "title": "推動跨國研究計畫，培植國際合作研究團隊，與頂尖研究單位合作"
        },
        {
          "page": [
            "47",
            "49"
          ],
          "paragraph": "統整雙方對合作計畫之具體規劃，包含研究合作、交換教師或學生、雙聯學程與其他相關合作計畫等，透過國際參訪與重點領域與教授專長的媒合，推動跨國研究團隊成立。",
          "title": "推動跨國研究計畫，培植國際合作研究團隊，與頂尖研究單位合作"
        }
      ],
      "成立跨國合作研究中心": [],
      "雙聯博士學位": [],
      "提供跨國進修機會": [
        {
          "page": [
            "20",
            "25"
          ],
          "paragraph": "擬定標準明確的頂尖音樂人才招生，並採「Pull & Push」培育藝術、文創、音樂人才，Pull是指延攬國際大師，Push是推動學生赴歐、美、日研修、實習或訪察研究。開辦藝術產業學分學程，協助學生結合理論與實務應用於多元產業，成為跨界人才。",
          "title": "延攬大師，培養藝術、文創、音樂的跨界人才，創造就業前景"
        }
      ],
      "強化師生國際交流": [
        {
          "page": [
            "47",
            "49"
          ],
          "paragraph": "為營造國際移動風氣，本校推動「一系一國際學術合作案」計畫，強調一系所一交換，每一系所自國外找一個相關的傑出系所進行標竿學習與深度合作，深化雙向學生交換、教師國際講學、合作研究之機制。",
          "title": "鼓勵系所進行國際合作研究，推動「一系一國際學術合作案」與「全球百大城市實質國際交流」計畫"
        }
      ],
      "招募國外博士後研究人才": []
    },
    "跨領域研究整合": {
      "跨領域合作研究案": [
        {
          "page": [
            "34",
            "47"
          ],
          "paragraph": "透過與標竿學校的競合，以領域帶動全校學術研究能量，探討最具影響力與挑戰性的教育研究議題，包含教育神經科學、智慧學習科技、智慧量測與教育大數據、科學教育議題，持續增進學術論文發表，維持本校在教育領域之領航地位。",
          "title": "持續深化教育領域研究成果，推展臺灣教育經驗"
        }
      ],
      "發展跨領域研究學群": [],
      "建立跨領域研究中心": []
    },
    "其他": {
      "充實硬體設備": [],
      "培育研究型人才": [],
      "強化學術研究倫理": []
    }
  },
  "產學": {
    "產學合作教學": {
      "開設產業專班/學院": [],
      "依產業需求研訂課程/學程規劃": [],
      "提升教師產業實務能力": [],
      "產業實務知識融入教學": [],
      "產業實務講座": [],
      "聘請業師或雙師協同教學": []
    },
    "建立/完善實習制度": {
      "建立/健全實習制度": [],
      "強化實習課程/實習講座": [],
      "檢驗/評估實習成果": [],
      "加強企業實習合作": [],
      "建立/強化企業實習平台": [],
      "拓展海外實習機會": []
    },
    "產學合作研究": {
      "與企業單位合作研究": [],
      "與企業合作設立研究中心": [],
      "產學研究獎勵制度": [],
      "修訂教師升等制度（強化產學研究）": [],
      "成立產學合作研究園區": []
    },
    "強化產學連結（不分教學研究）": {
      "建立/強化產學溝通管道": [],
      "成立/強化產學中心": [],
      "整合跨校區域產學資源": [],
      "拓展跨國產學合作": [],
      "建立產學合作制度": [
        {
          "page": [
            "66",
            "67"
          ],
          "paragraph": "將針對運動科學商品所需的科技與資料分析，進行大量的學術研究，期帶動國內運動科技輔具與商品之提升，與提供產業諮詢及輔導，提升產業競爭力，達到扶植國內運動休閒產業發展與推廣之成效。",
          "title": "以運動科學實證為基礎，開發運動休閒商品，滿足健康需求並創商機"
        },
        {
          "page": [
            "34",
            "47"
          ],
          "paragraph": "本校未來將運動機能用品的設計與運動科學結合，加入生物力學、運動醫學、人體工學概念的功能性設計，產出更貼合運動者需求的機能產品。",
          "title": "轉譯運動科學研究成果，融入運動產業"
        },
        {
          "page": [
            "34",
            "47"
          ],
          "paragraph": "利用在學術研究中理解的創新訊息加上運動科學中人體動作分析的概念，將研究成果轉譯為產品功能性設計，並與臺灣具有優秀研發與製造能力的廠商共同合作進而產出有保護功能，減少運動傷害，並提升運動表現的紡織機能用品。",
          "title": "轉譯運動科學研究成果，融入運動產業"
        },
        {
          "page": [
            "59",
            "64"
          ],
          "paragraph": "以USR計畫之「減塑『心』家園」為例，在產業方面，與「新浦樂生化科技股份有限公司」合作，製作環保材料與替代塑膠的生活用品，並由本校育成中心持續研發，同時擴展其他有志於減塑商品開發的組織。",
          "title": "促成產、官、學夥伴關係，加強資源連結與整合"
        },
        {
          "page": [
            "55",
            "58"
          ],
          "paragraph": "針對學校最具優勢或擁有專利技術之項目獨資成立公司經營，包含：藝術文創、華語文、教育、數位學習等相關事業。針對市場需求，與業界廠商合資成立公司，開發相關技術與商品，例如新能源、電動車等相關技術。搭配三創學程，針對師生研發成果，投資師生協助創業。",
          "title": "成立臺師大控股公司，平衡創資的正面價值與學術理想"
        }
      ]
    },
    "落實研發成果": {
      "成立/強化創新育成中心": [],
      "成立/強化產學運籌中心": [],
      "吸引創投基金": [
        {
          "page": [
            "30",
            "31"
          ],
          "paragraph": "本校已結合校務基金、誠正勤樸基金會、校友企業、外部企業，預定於106年12月設置臺師大新創控股事業股份有限公司，活絡校內創業創新氣氛。",
          "title": "成立新創事業投資控股公司，活絡校內創業創新氣氛"
        }
      ],
      "促進智財應用/技轉": [],
      "推動衍生企業環境": [],
      "扶植RSC新創事業": []
    },
    "其他": {
      "充實硬體設備": [],
      "開設職業倫理課程/講座": [],
      "技術開發": []
    }
  },
  "社會責任": {
    "與地方（或中央）政府連結": {
      "擔任政府智庫": [],
      "提供研究調查服務": [],
      "執行政策評估研究": [],
      "配合政策提供專業資訊/服務": [
        {
          "page": [
            "69",
            "71"
          ],
          "paragraph": "以專案承攬的方式，繼續協助政府辦理閩南語、客語及原住民語之語言能力認證考試，及本土語言專業人才培育工作。",
          "title": "配合政府政策，協助本土及原住民語言之倡導"
        },
        {
          "page": [
            "69",
            "71"
          ],
          "paragraph": "本校亦設有臺灣語言學系及原住民族研究發展中心，協助保存弱勢語言文化。",
          "title": "配合政府政策，協助本土及原住民語言之倡導"
        }
      ]
    },
    "與非營利組織（NPO）連結": {
      "參與了解NPO社會需求": [],
      "強化教師參與NPO": [],
      "強化學生參與NPO": []
    },
    "支援在地教育機構": {
      "支援在地中小學教育": [],
      "支援區域高中教育": [],
      "區域學習資源共享": [],
      "建置區域教學資源中心": []
    },
    "促進地區（社區）發展": {
      "參與了解地區（社區）需求": [
        {
          "page": [
            "59",
            "64"
          ],
          "paragraph": "敦聘相關領域人才擔任諮詢委員，定期召開諮詢委員會議，邀請校內執行大學社會責任計畫之教師報告推動狀況，以針對執行方向與成果進行交流與提供意見。",
          "title": "以學術副校長為首之行政組織推動大學社會責任"
        },
        {
          "page": [
            "59",
            "64"
          ],
          "paragraph": "每學期辦理多場次的「服務學習知能講座」，邀請不同領域的專家學者分享相關議題，培養學生具備服務學習的正確觀念與態度。",
          "title": "鼓勵、協助教師提出申請，開設大學社會責任服務課程"
        },
        {
          "page": [
            "20",
            "25"
          ],
          "paragraph": "全人書院讓來自不同院系成員，透過合作學習的小組討論，領導課程的學習與實踐及大師講座與對談，養成自主主動學習，並進行社會實踐／公益利他方案，將所學回饋社會。",
          "title": "推動多元型態特色書院制度"
        },
        {
          "page": [
            "34",
            "47"
          ],
          "paragraph": "本校將藉由主題活動辦理，帶動社區高齡者將本校做為高齡服務的軸心，整合地方各類服務能量與產業資源投入，達到互利、互助、共好、共享的效益",
          "title": "建立科學化之運動休閒模式的高齡者照護方法與實務，擴大社會貢獻"
        }
      ],
      "開設在地相關課程": [
        {
          "page": [
            "59",
            "64"
          ],
          "paragraph": "初期透過USR計畫進行課程調整，後續透過成果分享與教師同儕觀課，推廣融入USR精神的課程改造。",
          "title": "推動教師自身授課內容融入大學社會責任精神，並提供校內認證"
        },
        {
          "page": [
            "59",
            "64"
          ],
          "paragraph": "USR計畫之「深耕偏鄉弱勢教育」，也將偏遠地區學生特性、學校與社區需求、差異化教學或融合教育的理念與做法，推廣至特殊教育系、復健諮商研究所、體育學系、教育心理與輔導學系等相關系所的課程，鼓勵教師將課程內容與USR計畫相連結，體現系所的優勢與專長。",
          "title": "推動教師自身授課內容融入大學社會責任精神，並提供校內認證"
        },
        {
          "page": [
            "59",
            "64"
          ],
          "paragraph": "USR計畫之「PASSION（project of Adaptive Screening, Streaming, and Instruction）深耕偏鄉」，整合本校心測中心研發的學科診斷工具，並搭配通識中心、師培學院、文學院及理學院為補救教學量身規劃的課程，開設「PASSION偏鄉優質教育微學程」，培養師資生具備補救教學的專業素養與知識技能，完成課程要求者將核發證明。",
          "title": "整合現有課程規劃實施，推展大學社會責任學程或微學程"
        },
        {
          "page": [
            "59",
            "64"
          ],
          "paragraph": "持續開設「服務學習課程」，含括環境保育、社會人文、資訊科技等多面向之議題，協助學生達到知能啟發、深耕實作、學以致用及公民實踐的理想。",
          "title": "鼓勵、協助教師提出申請，開設大學社會責任服務課程"
        },
        {
          "page": [
            "59",
            "64"
          ],
          "paragraph": "朝向推動「服務學習課程教師培訓」，協助教師開設具服務學習內涵的專業課程，並充實教師帶領服務學習、多元反思及分享實作之教學技巧，並研發更多的服務學習標竿方案，豐富課程內容，達到善盡社會責任的目標。",
          "title": "鼓勵、協助教師提出申請，開設大學社會責任服務課程"
        }
      ],
      "協助在地社區規劃/改善": [
        {
          "page": [
            "59",
            "64"
          ],
          "paragraph": "本校PASSION團隊成立之「PASSION教學創新基地」，未來將轉型成兼顧企業盈餘、社會責任與環境責任的B型企業（B Corp）。",
          "title": "轉型B型企業與成立控股公司，永續延展計畫影響力"
        }
      ],
      "推廣/育成社會企業": [],
      "籌設藝文/活動中心": [
        {
          "page": [
            "69",
            "71"
          ],
          "paragraph": "持續辦理藝文活動，提供社區民眾高品質的藝術展演之外，即將於2018年啟用的師大美術館，亦將其周圍空間與在地文創產業連結，形塑大學美術館與社區之整體藝文氛圍。",
          "title": "打造在地藝術環境，提升國民藝術性靈"
        }
      ]
    },
    "提供在地服務": {
      "服務特定群體": [
        {
          "page": [
            "34",
            "47"
          ],
          "paragraph": "針對社區高齡民眾提供適合之飲食教案及執行共餐規劃模組，現場宣導過程中，也能跟地區組織互動，協助各單位共餐網絡資源之建立，了解社區高齡者共餐飲食之需求及第一線、即時性協助長者解決營養攝取、購買甚至管理上的問題，具體達到善盡大學社會責任的目標。",
          "title": "建立科學化之運動休閒模式的高齡者照護方法與實務，擴大社會貢獻"
        }
      ],
      "提供在地專業服務": [
        {
          "page": [
            "69",
            "71"
          ],
          "paragraph": "社區諮商中心方面，以三級輔導的概念結合在地化與專業化雙軌推動，協助本校師生融入在地人文與生活脈動，並與專業據點合作，以在地志工培力、健康講座、電影欣賞、讀書會及正念主題之行動性方案，落實在地服務模式。",
          "title": "成立「社區諮商中心」，協助社會大眾維持身心靈健康"
        },
        {
          "page": [
            "69",
            "71"
          ],
          "paragraph": "針對社區民眾提供心理測驗，辦理心理衛生講座與轉介服務，建立本校專有之心理諮商專業服務品牌。未來將朝向提供穩定個別心理諮商門診數、團體心理諮商、心理衛生講座、心理衛生諮詢服務等，形成「多元性經營」，逐步結合校內資源，以「全人」角度提供受服務者完整的專業服務，創造高倍率獲益成效。",
          "title": "成立「社區諮商中心」，協助社會大眾維持身心靈健康"
        }
      ],
      "發展/優化在地服務模式": [
        {
          "page": [
            "59",
            "64"
          ],
          "paragraph": "USR計畫之「建構高齡者長健全方位系統」，為增進學生在長健服務的專業知能與實作能力，推動高齡長健知能之學習護照，規劃「高齡長健基礎課程」、「高齡專業與通識融通課程」，以及「高齡長健實務操作見習與實習」，為助人工作者提供增能培訓。從系所既有開設的課程中，整合出與計畫目標相符的課程，以微學程的方式促進師生具備高齡者服務的能力，全方位關注實踐場域中高齡者生理、心理與社會需求。",
          "title": "整合現有課程規劃實施，推展大學社會責任學程或微學程"
        },
        {
          "page": [
            "59",
            "64"
          ],
          "paragraph": "「建構高齡者長健全方位系統」取得衛生福利部、鄰里辦公室等公部門資源、與八家以上的產業機構簽訂合作協議，以及校內外系所間的聯盟，為計畫的執行增添豐足的跨域資源。透過三方合作，打造產、官、學新夥伴鏈結關係，創造互利共贏的新合作模式。",
          "title": "促成產、官、學夥伴關係，加強資源連結與整合"
        },
        {
          "page": [
            "69",
            "71"
          ],
          "paragraph": "成立「銀齡樂活據點」之社區高齡者服務平台，引導大學生參與社區高齡者服務，實踐場域以本校所在之大安區為據點，延伸關懷周邊萬華、文山等高齡社區。",
          "title": "建構社區高齡者服務平台，引導大學生參與社區高齡服務"
        },
        {
          "page": [
            "69",
            "71"
          ],
          "paragraph": "志工服務方面，規劃「學生服務志工隊」實施代間教育，促進青老共餐及共學。",
          "title": "建構社區高齡者服務平台，引導大學生參與社區高齡服務"
        },
        {
          "page": [
            "69",
            "71"
          ],
          "paragraph": "成立「居家關懷照護服務隊」，定期關懷訪視與提供家具房屋修繕的服務，並運用學生志工的力量，進行健康飲食的宣導，以及連結各行政區健康服務中心，於社區舉辦代謝症候群篩檢活動。",
          "title": "建構社區高齡者服務平台，引導大學生參與社區高齡服務"
        },
        {
          "page": [
            "34",
            "47"
          ],
          "paragraph": "由夢想市集發想到具體3年規劃運作擴張後，預計創發高齡藝術教材、高齡益智互動遊戲APP、共餐餐包研發及文創產品產出等，期許更多資工產業、創新研發遊戲人才投入，以及研發餐包專業能量的注入，提升食品工廠連結及合作，而有這些外部資源的持續轉化，以及永續經營模式的建構，持續創新高齡產業的質與量提升。",
          "title": "建立科學化之運動休閒模式的高齡者照護方法與實務，擴大社會貢獻"
        }
      ],
      "發起/參與公益活動": [],
      "參與在地文化、藝術工程計畫": []
    },
    "打造永續校園": {
      "升級永續校園綠設施": [],
      "宣導永續校園概念及意識": [],
      "強化永續校園制度管理": [],
      "其他": []
    },
    "拓展國際社會服務": {
      "培植國際志工團隊": [],
      "擴充國際志工服務": [],
      "其他國際社會服務": []
    }
  },
  "大學治理與公共性": {
    "組織調整": {
      "組織定位及策略發展": [],
      "組織重構": [],
      "組織擴張": [],
      "增設組織單位": [
        {
          "page": [
            "59",
            "64"
          ],
          "paragraph": "本校將成立「大學社會責任實踐計畫辦公室」，由學術副校長擔任召集人，以達協調全校各單位之支援功能。",
          "title": "以學術副校長為首之行政組織推動大學社會責任"
        }
      ],
      "裁撤組織單位": [],
      "學院實體化方案": []
    },
    "強化招生": {
      "辦理高中生活動": [],
      "辦理特殊選才": [
        {
          "page": [
            "34",
            "47"
          ],
          "paragraph": "本校音樂學系針對特殊選才招生進行研究與策略制定，研究世界各主要國家頂尖音樂人才培育制度",
          "title": "延攬國際級藝術人文大師，開創特殊選才招生，培育頂尖藝術人才"
        }
      ],
      "強化僑生、港澳生招生": [],
      "拓展國外生源": [],
      "設計招生制度性誘因": []
    },
    "拓展財源": {
      "企業募款": [],
      "經營校友會、系友會": [],
      "調整學費": [],
      "爭取政府經費補助": [],
      "爭取非政府單位經費補助": [],
      "強化進修推廣教育營收": [],
      "附加營收多樣化": [],
      "校務基金管理投資衍生收入": []
    },
    "境外拓展": {
      "與國外學校合作開設境外學程或課程": [],
      "與國外學校合作開設境外學位學程": [],
      "開設境外分校": []
    },
    "健全財務管理制度": {
      "精簡行政縮減開支": [],
      "資源分配控管制度化": [],
      "建立財務透明稽核制度": [],
      "校務基金決策機制透明化": []
    },
    "推動校務研究（IR）": {
      "建置校務資料系統": [
        {
          "page": [
            "55",
            "58"
          ],
          "paragraph": "透過校務研究資料庫之建置，將各單位資料逐步串接，建立全校的資料倉儲，協助各單位進行校務議題自主分析，亦定期舉辦教育訓練，增強行政組織學習力與以據為策的行政能力。",
          "title": "透明化校務資訊，保障教職員工生及大眾知的權利"
        },
        {
          "page": [
            "55",
            "58"
          ],
          "paragraph": "建置校務研究資料庫之軟硬體環境，與搭建學校各項公開資訊儀表版。未來朝向透過舉辦教育訓練，增強行政組織學習力與「以據為策」的行政能力，透過校務發展預測模型，做為教學與輔導機制和學校資源投入之調整依據，達學校跨單位合作、知識管理與資源之有效投入。",
          "title": "發展大數據資料庫，優化高等教育議題的分析與預測技術"
        },
        {
          "page": [
            "31",
            "33"
          ],
          "paragraph": "與資訊中心合作將各單位的個別資料庫利用人事編號或是學號串接，建立去個資化的整合中繼資料庫，建立整合資料分析平台，作為校務資訊的彙整者與提供者。",
          "title": "完備校務研究（IR）體系，定期巡視校務資料並提供檢測報告建議，持續追蹤學生學習成效，提供校務發展之證據基礎"
        }
      ],
      "成立校務研究中心": [],
      "發展校務研究": [
        {
          "page": [
            "55",
            "58"
          ],
          "paragraph": "並利用數據進行特定議題之分析，達宣揚本校研究與辦學成效，提升本校能見度與競爭力。",
          "title": "透明化校務資訊，保障教職員工生及大眾知的權利"
        },
        {
          "page": [
            "55",
            "58"
          ],
          "paragraph": "建立學習歷程檔案運用模式，協助學生規劃成功學習藍圖，擷取分析系統資料提供校務研究參考。",
          "title": "設立「學生數位學習歷程檔案系統」，完整本校學生的學涯履歷"
        },
        {
          "page": [
            "31",
            "33"
          ],
          "paragraph": "為落實成全校性校務研究的文化，將健全發展校務研究辦公室的功能與研發能量，培育校務研究人才，協同其他單位之校務研究，成立跨單位的共同工作圈。",
          "title": "完備校務研究（IR）體系，定期巡視校務資料並提供檢測報告建議，持續追蹤學生學習成效，提供校務發展之證據基礎"
        }
      ]
    },
    "健全改革董事會（私校）": {
      "設定董事長及董事任期": [],
      "聘任公益或獨立董事": [],
      "董事遴選制度公開透明": []
    },
    "健全大學治理參與制度": {
      "建立資訊公開透明機制": [],
      "健全學生參與機制": [],
      "健全互動關係人參與機制": []
    },
    "增加弱勢生入學機會": {
      "擴大繁星入學管道": [],
      "增加身心障礙生入學機會": [],
      "招收原住民學生/新移民子女": [],
      "增加弱勢家庭子女入學機會": [
        {
          "page": [
            "51",
            "55"
          ],
          "paragraph": "在弱勢招生方面，朝向訂定年度招收弱勢學生目標，招生辦公室也將進行弱勢學生生源專案分析與相關研究，持續改善晨光計畫各系優先録取弱勢生機制，增加弱勢學生申請備取名額。",
          "title": "擴增弱勢生入學管道，落實校園多元化與社會公平正義"
        },
        {
          "page": [
            "51",
            "55"
          ],
          "paragraph": "部分系所以優先錄取低收入、中低收入或特殊境遇家庭學生為策略，提供弱勢生學習上的保障。",
          "title": "擴增弱勢生入學管道，落實校園多元化與社會公平正義"
        },
        {
          "page": [
            "51",
            "55"
          ],
          "paragraph": "自107學年度起於特殊選才管道中，提供優先錄取不同教育資歷學生（含新住民及子女之經濟弱勢學生）的機制，預計每年以3%的成長比率增加。",
          "title": "創設「晨光雙管道入學」計畫，提供經濟弱勢學子未來發展契機"
        }
      ]
    },
    "弱勢學生支持系統": {
      "弱勢學生獎補助制度": [
        {
          "page": [
            "51",
            "55"
          ],
          "paragraph": "設置「各學系所特色發展獎助學金」，引導學生積極規劃學習計畫，獎助項目包含論文學習、教學獎助、學習活動補助、獎學金、生活助學金等，引導學生積極規劃學習計畫。",
          "title": "建立發展性獎學基金，促進學生學習投入與自我實現"
        },
        {
          "page": [
            "51",
            "55"
          ],
          "paragraph": "本校設置多元獎助金，給予不同狀況的弱勢生適時的幫助。積極建立弱勢助學之外部資源（matching fund），設置多元獎助金以提供弱勢學生之生活與學習資助。",
          "title": "豐厚生活扶助機制，實踐照護責任公共化之理想"
        }
      ],
      "建立/強化弱勢生支持系統": [
        {
          "page": [
            "51",
            "55"
          ],
          "paragraph": "建立弱勢學生學習輔導機制，獎勵弱勢學生出國學習，擴展國際視野。",
          "title": "擴增弱勢生入學管道，落實校園多元化與社會公平正義"
        },
        {
          "page": [
            "51",
            "55"
          ],
          "paragraph": "建立以「學生學習」需要為主體的輔導機制，使經濟弱勢學生得以同時兼顧課業與生活所需，並開設「生活技能工作坊」等學習方案，增進弱勢學生語文、資訊與社會適應之技能。",
          "title": "豐厚生活扶助機制，實踐照護責任公共化之理想"
        },
        {
          "page": [
            "51",
            "55"
          ],
          "paragraph": "由專責導師輪值擔任住校輔導，處理學生緊急事件。並透過班級活動、導生聚會、個別談話及學生請假審查等各種時機掌握學生狀況，適時提供相關資源或轉介相關單位。",
          "title": "首創「專責導師制度」，強化大學生心理健康素養與危機事件處理"
        },
        {
          "page": [
            "51",
            "55"
          ],
          "paragraph": "在學習方面，與各學系及教學發展中心共同進行學生的追蹤輔導，並建立弱勢學生的連絡網，協助教學發展中心及生活輔導組辦理相關講座與工作坊。",
          "title": "首創「專責導師制度」，強化大學生心理健康素養與危機事件處理"
        },
        {
          "page": [
            "51",
            "55"
          ],
          "paragraph": "「原住民學生資源中心」透過專責導師個別約談、導生聚會等各種時機，加強原住民學生生活及學習輔導，協助生活適應與安心就學，並持續舉辦原住民議題相關活動，深耕原住民學生對傳統文化的理解與實踐。",
          "title": "設立多元輔導管道，推展具支持性的生活與學習扶助"
        },
        {
          "page": [
            "51",
            "55"
          ],
          "paragraph": "「特殊教育推行委員會」除了積極建立無障礙環境和學習支持外，經由體適能評估，養成特殊學生健康習慣，也鼓勵學生參與社團及與國內外身心障礙大學生交流，以增進學生的實踐力、就業力和社會責任。",
          "title": "設立多元輔導管道，推展具支持性的生活與學習扶助"
        },
        {
          "page": [
            "51",
            "55"
          ],
          "paragraph": "「晨光學習輔導計畫」鼓勵弱勢學生參與課程、研究或教師社群，藉由與教師直接互動，學習專業知識與技能，並與輔導教師談話探索自己的生涯發展。",
          "title": "設立多元輔導管道，推展具支持性的生活與學習扶助"
        },
        {
          "page": [
            "51",
            "55"
          ],
          "paragraph": "未來將透過「晨光閱讀志工培訓與服務」，強化與統整學生的組織與領導能力，讓晨光團隊踏入偏鄉，以閱讀服務提升偏遠地區學童的基礎語文能力，進而實踐社會關懷價值。",
          "title": "設立多元輔導管道，推展具支持性的生活與學習扶助"
        },
        {
          "page": [
            "55",
            "58"
          ],
          "paragraph": "協助企業與學校建立長久產學合作關係，提供弱勢學生實習與就業機會；並將投資獲利回饋，轉為創設永續性的弱勢學生助學基金，實現教育機會均等與企業人才培育之理想目標。",
          "title": "成立臺師大控股公司，平衡創資的正面價值與學術理想"
        },
        {
          "page": [
            "64",
            "65"
          ],
          "paragraph": "藉由遠端支持系統進行資料分析與監控，提供身障生適性之篩選、轉介、鑑定與安置，支援金門縣、連江縣等偏遠地區的融合教育發展。",
          "title": "研發多元診斷系統，提供適性教學，以回應特殊需求、弭平成就落差"
        },
        {
          "page": [
            "59",
            "64"
          ],
          "paragraph": "預計將研發的教學模組和相關教材教法商業化，所得盈餘適當分配給弱勢家庭和學生，改善弱勢族群的學習環境，達計畫永續經營之目的。",
          "title": "轉型B型企業與成立控股公司，永續延展計畫影響力"
        }
      ],
      "建立外部募款基金": []
    },
    "其他": {
      "建置開放式線上課程": [],
      "平衡人文社會及自然科學領域發展": [],
      "強化行政職能": [
        {
          "page": [
            "47",
            "49"
          ],
          "paragraph": "本校將持續每年擬訂赴國外標竿參訪計畫，使行政同仁得以與標竿大學進行交流回饋，從中反思本校目前政策與相關措施，從而借鏡學習，以收見賢思齊之效，進而提升行政品質與效率。",
          "title": "推動校務行政標竿學習，師法國際名校"
        }
      ],
      "建立計畫管考機制": [
        {
          "page": [
            "55",
            "58"
          ],
          "paragraph": "由各單位自主提出列管事項，並配合學校規劃的追蹤列管系統，定期填報進度與業務訊息。經由校長主持管考會議，針對各項校務發展重點進行綜合評估，協助行政人員理解自我職責與校務發展目標的關聯，促使學校各單位的連結，與貫徹學校總體發展。",
          "title": "推展「PDCA管考機制與結合平衡計分卡之團體績效評分系統」，優化行政效能使符合社會期待"
        },
        {
          "page": [
            "55",
            "58"
          ],
          "paragraph": "未來將結合行政單位服務滿意度調查，並納入當年度行政單位團體績效考核，持續追蹤未達指標單位的執行情形，具體落實PDCA循環之品質保證機制。",
          "title": "推展「PDCA管考機制與結合平衡計分卡之團體績效評分系統」，優化行政效能使符合社會期待"
        }
      ],
      "基礎建設及硬體設備提升": [],
      "提升學校知名度": [
        {
          "page": [
            "47",
            "49"
          ],
          "paragraph": "本校將持續追求創新，打造具有特色之行政措施，並鼓勵各單位多利用本校公共事務中心，協助校園新聞採訪，透過本校新聞剪報系統，可吸引其他大學慕名交流，未來將與google系統合作，提高本校正面新聞網路搜尋及曝光量，強化本校的國際能見度和影響力。",
          "title": "推動行政措施海外影響力"
        }
      ],
      "增進師生福利": []
    }
  }
}